__init__.py
main.py
distrolock-0.9.0.dist-info/LICENSE
distrolock-0.9.0.dist-info/METADATA
distrolock-0.9.0.dist-info/WHEEL
distrolock-0.9.0.dist-info/top_level.txt
distrolock-0.9.0.dist-info/RECORD
