Metadata-Version: 2.1
Name: distrolock
Version: 0.9.0
Summary: Serverless distributable authentication.
Author: ColonelParrot
License: MIT License
Project-URL: Homepage, https://github.com/ColonelParrot/distrolock
Keywords: authentication,distributable,serverless
Classifier: License :: OSI Approved :: MIT License
Classifier: Programming Language :: Python
Classifier: Programming Language :: Python :: 3
Requires-Python: >=3.9
License-File: LICENSE
Requires-Dist: pillow >=10.2.0
Requires-Dist: requests >=2.31.0
